Tool.py
onelib/__init__.py
onelib/libone.py
lynlibtest-1.0.0.dist-info/LICENSE.txt
lynlibtest-1.0.0.dist-info/METADATA
lynlibtest-1.0.0.dist-info/WHEEL
lynlibtest-1.0.0.dist-info/top_level.txt
lynlibtest-1.0.0.dist-info/RECORD
