Metadata-Version: 2.1
Name: lynlibtest
Version: 1.0.0
Summary: this is lyn's first lib
Home-page: https://github.com/OldboyFzZF
Author: Lyn
Author-email: lyn207@163.com
License: MIT
Platform: UNKNOWN
